{
  "_instruction": "vocabulary layer — อ่านก่อนสกัด rules จากตำรา",

  "aspect_terms": {
    "กุม": "conjunction",
    "เล็ง": "opposition",
    "ตรีโกณ": "trine",
    "จตุรัส": "square",
    "โยค": "combination",
    "สัมพันธ์": "aspect_general",
    "ร่วมราศี": "conjunction",
    "ตรงข้าม": "opposition",
    "ทับ": "conjunction_exact"
  },

  "quality_terms": {
    "เกษตร": "domicile",
    "ประเกษตร": "detriment",
    "อุจ": "exaltation",
    "อุจจ์": "exaltation",
    "นิจ": "fall",
    "มูลตรีโกณ": "mulatrikona",
    "มหาจักร": "maha_chakra",
    "จุลจักร": "chula_chakra",
    "ราชาโชค": "racha_chok",
    "เทวีโชค": "thewi_chok",
    "อุจจาวิลาส": "uchcha_wilas",
    "อุจจาภิมุข": "uchcha_phimuk"
  },

  "planet_synonyms": {
    "พระอาทิตย์": 1, "ดาวอาทิตย์": 1, "อา": 1,
    "พระจันทร์": 2, "ดาวจันทร์": 2, "จ": 2,
    "ดาวอังคาร": 3, "พระอังคาร": 3, "อ": 3,
    "ดาวพุธ": 4, "พระพุธ": 4, "พ": 4,
    "ดาวพฤหัส": 5, "พระพฤหัส": 5, "ฤ": 5, "พฤหัสบดี": 5,
    "ดาวศุกร์": 6, "พระศุกร์": 6, "ศ": 6,
    "ดาวเสาร์": 7, "พระเสาร์": 7, "ส": 7,
    "ราหู": 8, "พระราหู": 8, "รา": 8,
    "เกตุ": 9, "พระเกตุ": 9, "เก": 9,
    "มฤตยู": 0
  },

  "prediction_verbs": [
    "ให้", "ทำให้", "จะได้", "มักจะ", "ส่งผลให้",
    "เป็นเหตุให้", "ย่อมได้", "จะมี", "ทำนายว่า",
    "พยากรณ์ว่า", "บ่งบอกว่า", "ชี้ให้เห็นว่า"
  ],

  "polarity_signals": {
    "positive": ["ดี", "มั่งคั่ง", "โชคดี", "สำเร็จ", "มีโชค", "เจริญ", "ได้ลาภ"],
    "negative": ["ร้าย", "เสียหาย", "ทุกข์", "โทษ", "อันตราย", "สูญเสีย", "พินาศ"],
    "mixed": ["ขึ้นอยู่กับ", "แล้วแต่", "บางครั้ง", "ในบางกรณี"]
  },

  "source_type_signals": {
    "PRIMARY": ["ตำรากล่าวว่า", "โหรากล่าวว่า", "ว่าไว้ว่า", "กล่าวตรงๆ"],
    "INFERRED": ["น่าจะ", "derive จาก", "รวมกับ", "ผสมกัน", "เกิดความหมายใหม่"]
  },

  "tokenization_rules": {
    "split_on": ["และ", "หรือ", "แต่", "ถ้า", "เมื่อ", "เพราะ"],
    "keep_together": ["ดาวอาทิตย์", "ดาวจันทร์", "ดาวอังคาร"],
    "ignore": ["ครั้น", "แล", "นั้น", "อัน", "ซึ่ง"]
  }
}
