{
  "title": "EP09 ดาวบนฟ้าส่งพลังถึงกันได้ยังไง?  4 มุมสัมพันธ์ กุม เล็ง โยก ตรีโกณ | โหราศาสตร์ไทย",
  "body": "ดาวบนฟ้าส่งพลังถึงกันได้ยังไง?  4 มุมสัมพันธ์ กุม เล็ง โยก ตรีโกณ | โหราศาสตร์ไทย (5 นาที)\n\nเคยสงสัยไหมว่าทำไมดาวที่อยู่คนละราศีถึงมีอิทธิพลต่อกันได้? ในตอนที่ 9 นี้ เราจะพาคุณไปเจาะลึกกลไกที่เปรียบเสมือน \"เสาสัญญาณวิทยุจักรวาล\" นั่นคือ มุมสัมพันธ์ทั้ง 4 รูปแบบที่จะบอกว่าดาวดวงไหนกำลังส่งแรงกระเพื่อมถึงชีวิตคุณแรงแค่ไหน\n\n▶️ ดูวิดีโอเต็ม: https://www.youtube.com/watch?v=RVCseNniE4c\n\n#โหราศาสตร์ไทย #TALS #โหราทาส #HoratadAI",
  "category": "education",
  "source": "youtube",
  "tags": [
    "โหราศาสตร์ไทย",
    "TALS"
  ],
  "date_added": "2026-05-28",
  "priority_score": 7,
  "status": "scheduled",
  "meta": {
    "youtube_video_id": "RVCseNniE4c",
    "youtube_url": "https://www.youtube.com/watch?v=RVCseNniE4c",
    "youtube_thumbnail": "https://i.ytimg.com/vi/RVCseNniE4c/maxresdefault.jpg",
    "youtube_published_at": "2026-05-05T19:07:53Z",
    "duration_minutes": 5,
    "episode": 9
  },
  "scheduled_at": "2026-05-29T09:55:48.165Z"
}